{
	"incidentFields": [
		{
			"id": "incident_airsapplicationname",
			"version": 0,
			"cacheVersn": 0,
			"modified": "2026-05-06T07:19:07.296846631Z",
			"sizeInBytes": 0,
			"packID": "",
			"packName": "",
			"itemVersion": "",
			"fromServerVersion": "",
			"toServerVersion": "",
			"definitionId": "",
			"isOverridable": false,
			"vcShouldIgnore": false,
			"vcShouldKeepItemLegacyProdMachine": false,
			"commitMessage": "",
			"shouldCommit": false,
			"name": "AIRS Application Name",
			"prevName": "",
			"ownerOnly": false,
			"placeholder": "",
			"template": "",
			"description": "",
			"cliName": "airsapplicationname",
			"type": "shortText",
			"orgType": "shortText",
			"closeForm": false,
			"editForm": true,
			"required": false,
			"script": "",
			"runScriptAfterUpdate": false,
			"fieldCalcScript": "",
			"neverSetAsRequired": false,
			"isReadOnly": false,
			"selectValues": null,
			"autoCompleteTags": null,
			"validationRegex": "",
			"x2_fields": "",
			"useAsKpi": false,
			"locked": false,
			"system": false,
			"content": false,
			"group": 0,
			"mergeStrategy": "",
			"hidden": false,
			"openEnded": false,
			"associatedTypes": [
				"Prisma AIRS Violation"
			],
			"systemAssociatedTypes": null,
			"associatedToAll": false,
			"unmapped": false,
			"unsearchable": true,
			"caseInsensitive": false,
			"columns": null,
			"defaultRows": null,
			"sla": 0,
			"threshold": 72,
			"breachScript": "",
			"validatedError": "",
			"aliases": null,
			"aliasTo": "",
			"XDRBuiltInField": false,
			"selectValuesMap": null,
			"ipVersion": "",
			"pretty_name": "AIRS Application Name",
			"XDRSpecialUpdateFlowField": false,
			"XsiamIncidentFieldExtraData": null
		},
		{
			"id": "incident_airsdetectors",
			"version": 0,
			"cacheVersn": 0,
			"modified": "2026-05-06T07:19:07.296848448Z",
			"sizeInBytes": 0,
			"packID": "",
			"packName": "",
			"itemVersion": "",
			"fromServerVersion": "",
			"toServerVersion": "",
			"definitionId": "",
			"isOverridable": false,
			"vcShouldIgnore": false,
			"vcShouldKeepItemLegacyProdMachine": false,
			"commitMessage": "",
			"shouldCommit": false,
			"name": "AIRS Detectors",
			"prevName": "",
			"ownerOnly": false,
			"placeholder": "",
			"template": "",
			"description": "",
			"cliName": "airsdetectors",
			"type": "shortText",
			"orgType": "shortText",
			"closeForm": false,
			"editForm": true,
			"required": false,
			"script": "",
			"runScriptAfterUpdate": false,
			"fieldCalcScript": "",
			"neverSetAsRequired": false,
			"isReadOnly": false,
			"selectValues": null,
			"autoCompleteTags": null,
			"validationRegex": "",
			"x2_fields": "",
			"useAsKpi": false,
			"locked": false,
			"system": false,
			"content": false,
			"group": 0,
			"mergeStrategy": "",
			"hidden": false,
			"openEnded": false,
			"associatedTypes": [
				"Prisma AIRS Violation"
			],
			"systemAssociatedTypes": null,
			"associatedToAll": false,
			"unmapped": false,
			"unsearchable": true,
			"caseInsensitive": true,
			"columns": null,
			"defaultRows": null,
			"sla": 0,
			"threshold": 72,
			"breachScript": "",
			"validatedError": "",
			"aliases": null,
			"aliasTo": "",
			"XDRBuiltInField": false,
			"selectValuesMap": null,
			"ipVersion": "",
			"pretty_name": "AIRS Detectors",
			"XDRSpecialUpdateFlowField": false,
			"XsiamIncidentFieldExtraData": null
		},
		{
			"id": "incident_airsenvironment",
			"version": 0,
			"cacheVersn": 0,
			"modified": "2026-05-06T07:19:07.296853039Z",
			"sizeInBytes": 0,
			"packID": "",
			"packName": "",
			"itemVersion": "",
			"fromServerVersion": "",
			"toServerVersion": "",
			"definitionId": "",
			"isOverridable": false,
			"vcShouldIgnore": false,
			"vcShouldKeepItemLegacyProdMachine": false,
			"commitMessage": "",
			"shouldCommit": false,
			"name": "AIRS Environment",
			"prevName": "",
			"ownerOnly": false,
			"placeholder": "",
			"template": "",
			"description": "",
			"cliName": "airsenvironment",
			"type": "shortText",
			"orgType": "",
			"closeForm": false,
			"editForm": true,
			"required": false,
			"script": "",
			"runScriptAfterUpdate": false,
			"fieldCalcScript": "",
			"neverSetAsRequired": false,
			"isReadOnly": false,
			"selectValues": null,
			"autoCompleteTags": null,
			"validationRegex": "",
			"x2_fields": "",
			"useAsKpi": false,
			"locked": false,
			"system": false,
			"content": false,
			"group": 0,
			"mergeStrategy": "",
			"hidden": false,
			"openEnded": false,
			"associatedTypes": null,
			"systemAssociatedTypes": null,
			"associatedToAll": true,
			"unmapped": false,
			"unsearchable": false,
			"caseInsensitive": true,
			"columns": null,
			"defaultRows": null,
			"sla": 0,
			"threshold": 72,
			"breachScript": "",
			"validatedError": "",
			"aliases": null,
			"aliasTo": "",
			"XDRBuiltInField": false,
			"selectValuesMap": null,
			"ipVersion": "",
			"pretty_name": "AIRS Environment",
			"XDRSpecialUpdateFlowField": false,
			"XsiamIncidentFieldExtraData": {
				"incidentsFilter": null,
				"slaGoals": null,
				"slaTimer": null,
				"timerConditions": null
			}
		},
		{
			"id": "incident_airsmodelname",
			"version": 0,
			"cacheVersn": 0,
			"modified": "2026-05-06T07:19:07.296853741Z",
			"sizeInBytes": 0,
			"packID": "",
			"packName": "",
			"itemVersion": "",
			"fromServerVersion": "",
			"toServerVersion": "",
			"definitionId": "",
			"isOverridable": false,
			"vcShouldIgnore": false,
			"vcShouldKeepItemLegacyProdMachine": false,
			"commitMessage": "",
			"shouldCommit": false,
			"name": "AIRS Model Name",
			"prevName": "",
			"ownerOnly": false,
			"placeholder": "",
			"template": "",
			"description": "",
			"cliName": "airsmodelname",
			"type": "shortText",
			"orgType": "",
			"closeForm": false,
			"editForm": true,
			"required": false,
			"script": "",
			"runScriptAfterUpdate": false,
			"fieldCalcScript": "",
			"neverSetAsRequired": false,
			"isReadOnly": false,
			"selectValues": null,
			"autoCompleteTags": null,
			"validationRegex": "",
			"x2_fields": "",
			"useAsKpi": false,
			"locked": false,
			"system": false,
			"content": false,
			"group": 0,
			"mergeStrategy": "",
			"hidden": false,
			"openEnded": false,
			"associatedTypes": null,
			"systemAssociatedTypes": null,
			"associatedToAll": true,
			"unmapped": false,
			"unsearchable": false,
			"caseInsensitive": true,
			"columns": null,
			"defaultRows": null,
			"sla": 0,
			"threshold": 72,
			"breachScript": "",
			"validatedError": "",
			"aliases": null,
			"aliasTo": "",
			"XDRBuiltInField": false,
			"selectValuesMap": null,
			"ipVersion": "",
			"pretty_name": "AIRS Model Name",
			"XDRSpecialUpdateFlowField": false,
			"XsiamIncidentFieldExtraData": {
				"incidentsFilter": null,
				"slaGoals": null,
				"slaTimer": null,
				"timerConditions": null
			}
		},
		{
			"id": "incident_airsprofilename",
			"version": 0,
			"cacheVersn": 0,
			"modified": "2026-05-06T07:19:07.296848922Z",
			"sizeInBytes": 0,
			"packID": "",
			"packName": "",
			"itemVersion": "",
			"fromServerVersion": "",
			"toServerVersion": "",
			"definitionId": "",
			"isOverridable": false,
			"vcShouldIgnore": false,
			"vcShouldKeepItemLegacyProdMachine": false,
			"commitMessage": "",
			"shouldCommit": false,
			"name": "AIRS Profile Name",
			"prevName": "",
			"ownerOnly": false,
			"placeholder": "",
			"template": "",
			"description": "",
			"cliName": "airsprofilename",
			"type": "shortText",
			"orgType": "shortText",
			"closeForm": false,
			"editForm": true,
			"required": false,
			"script": "",
			"runScriptAfterUpdate": false,
			"fieldCalcScript": "",
			"neverSetAsRequired": false,
			"isReadOnly": false,
			"selectValues": null,
			"autoCompleteTags": null,
			"validationRegex": "",
			"x2_fields": "",
			"useAsKpi": false,
			"locked": false,
			"system": false,
			"content": false,
			"group": 0,
			"mergeStrategy": "",
			"hidden": false,
			"openEnded": false,
			"associatedTypes": [
				"Prisma AIRS Violation"
			],
			"systemAssociatedTypes": null,
			"associatedToAll": false,
			"unmapped": false,
			"unsearchable": true,
			"caseInsensitive": false,
			"columns": null,
			"defaultRows": null,
			"sla": 0,
			"threshold": 72,
			"breachScript": "",
			"validatedError": "",
			"aliases": null,
			"aliasTo": "",
			"XDRBuiltInField": false,
			"selectValuesMap": null,
			"ipVersion": "",
			"pretty_name": "AIRS Profile Name",
			"XDRSpecialUpdateFlowField": false,
			"XsiamIncidentFieldExtraData": null
		},
		{
			"id": "incident_airsprompt",
			"version": 0,
			"cacheVersn": 0,
			"modified": "2026-05-06T07:19:07.296849608Z",
			"sizeInBytes": 0,
			"packID": "",
			"packName": "",
			"itemVersion": "",
			"fromServerVersion": "",
			"toServerVersion": "",
			"definitionId": "",
			"isOverridable": false,
			"vcShouldIgnore": false,
			"vcShouldKeepItemLegacyProdMachine": false,
			"commitMessage": "",
			"shouldCommit": false,
			"name": "AIRS Prompt",
			"prevName": "",
			"ownerOnly": false,
			"placeholder": "",
			"template": "",
			"description": "",
			"cliName": "airsprompt",
			"type": "longText",
			"orgType": "longText",
			"closeForm": false,
			"editForm": true,
			"required": false,
			"script": "",
			"runScriptAfterUpdate": false,
			"fieldCalcScript": "",
			"neverSetAsRequired": false,
			"isReadOnly": false,
			"selectValues": null,
			"autoCompleteTags": null,
			"validationRegex": "",
			"x2_fields": "",
			"useAsKpi": false,
			"locked": false,
			"system": false,
			"content": false,
			"group": 0,
			"mergeStrategy": "",
			"hidden": false,
			"openEnded": false,
			"associatedTypes": [
				"Prisma AIRS Violation"
			],
			"systemAssociatedTypes": null,
			"associatedToAll": false,
			"unmapped": false,
			"unsearchable": true,
			"caseInsensitive": true,
			"columns": null,
			"defaultRows": null,
			"sla": 0,
			"threshold": 72,
			"breachScript": "",
			"validatedError": "",
			"aliases": null,
			"aliasTo": "",
			"XDRBuiltInField": false,
			"selectValuesMap": null,
			"ipVersion": "",
			"pretty_name": "AIRS Prompt",
			"XDRSpecialUpdateFlowField": false,
			"XsiamIncidentFieldExtraData": null
		},
		{
			"id": "incident_airssessionid",
			"version": 0,
			"cacheVersn": 0,
			"modified": "2026-05-06T07:19:07.296849924Z",
			"sizeInBytes": 0,
			"packID": "",
			"packName": "",
			"itemVersion": "",
			"fromServerVersion": "",
			"toServerVersion": "",
			"definitionId": "",
			"isOverridable": false,
			"vcShouldIgnore": false,
			"vcShouldKeepItemLegacyProdMachine": false,
			"commitMessage": "",
			"shouldCommit": false,
			"name": "AIRS Session ID",
			"prevName": "",
			"ownerOnly": false,
			"placeholder": "",
			"template": "",
			"description": "",
			"cliName": "airssessionid",
			"type": "shortText",
			"orgType": "shortText",
			"closeForm": false,
			"editForm": true,
			"required": false,
			"script": "",
			"runScriptAfterUpdate": false,
			"fieldCalcScript": "",
			"neverSetAsRequired": false,
			"isReadOnly": false,
			"selectValues": null,
			"autoCompleteTags": null,
			"validationRegex": "",
			"x2_fields": "",
			"useAsKpi": false,
			"locked": false,
			"system": false,
			"content": false,
			"group": 0,
			"mergeStrategy": "",
			"hidden": false,
			"openEnded": false,
			"associatedTypes": [
				"Prisma AIRS Violation"
			],
			"systemAssociatedTypes": null,
			"associatedToAll": false,
			"unmapped": false,
			"unsearchable": true,
			"caseInsensitive": false,
			"columns": null,
			"defaultRows": null,
			"sla": 0,
			"threshold": 72,
			"breachScript": "",
			"validatedError": "",
			"aliases": null,
			"aliasTo": "",
			"XDRBuiltInField": false,
			"selectValuesMap": null,
			"ipVersion": "",
			"pretty_name": "AIRS Session ID",
			"XDRSpecialUpdateFlowField": false,
			"XsiamIncidentFieldExtraData": null
		},
		{
			"id": "incident_airsthreatsnippets",
			"version": 0,
			"cacheVersn": 0,
			"modified": "2026-05-06T07:19:07.296850341Z",
			"sizeInBytes": 0,
			"packID": "",
			"packName": "",
			"itemVersion": "",
			"fromServerVersion": "",
			"toServerVersion": "",
			"definitionId": "",
			"isOverridable": false,
			"vcShouldIgnore": false,
			"vcShouldKeepItemLegacyProdMachine": false,
			"commitMessage": "",
			"shouldCommit": false,
			"name": "AIRS Threat Snippets",
			"prevName": "",
			"ownerOnly": false,
			"placeholder": "",
			"template": "",
			"description": "",
			"cliName": "airsthreatsnippets",
			"type": "markdown",
			"orgType": "markdown",
			"closeForm": false,
			"editForm": true,
			"required": false,
			"script": "",
			"runScriptAfterUpdate": false,
			"fieldCalcScript": "",
			"neverSetAsRequired": false,
			"isReadOnly": false,
			"selectValues": null,
			"autoCompleteTags": null,
			"validationRegex": "",
			"x2_fields": "",
			"useAsKpi": false,
			"locked": false,
			"system": false,
			"content": false,
			"group": 0,
			"mergeStrategy": "",
			"hidden": false,
			"openEnded": false,
			"associatedTypes": [
				"Prisma AIRS Violation"
			],
			"systemAssociatedTypes": null,
			"associatedToAll": false,
			"unmapped": false,
			"unsearchable": true,
			"caseInsensitive": true,
			"columns": null,
			"defaultRows": null,
			"sla": 0,
			"threshold": 72,
			"breachScript": "",
			"validatedError": "",
			"aliases": null,
			"aliasTo": "",
			"XDRBuiltInField": false,
			"selectValuesMap": null,
			"ipVersion": "",
			"pretty_name": "AIRS Threat Snippets",
			"XDRSpecialUpdateFlowField": false,
			"XsiamIncidentFieldExtraData": null
		},
		{
			"id": "incident_airstsgid",
			"version": 0,
			"cacheVersn": 0,
			"modified": "2026-05-06T07:19:07.296850724Z",
			"sizeInBytes": 0,
			"packID": "",
			"packName": "",
			"itemVersion": "",
			"fromServerVersion": "",
			"toServerVersion": "",
			"definitionId": "",
			"isOverridable": false,
			"vcShouldIgnore": false,
			"vcShouldKeepItemLegacyProdMachine": false,
			"commitMessage": "",
			"shouldCommit": false,
			"name": "AIRS TSG ID",
			"prevName": "",
			"ownerOnly": false,
			"placeholder": "",
			"template": "",
			"description": "",
			"cliName": "airstsgid",
			"type": "shortText",
			"orgType": "shortText",
			"closeForm": false,
			"editForm": true,
			"required": false,
			"script": "",
			"runScriptAfterUpdate": false,
			"fieldCalcScript": "",
			"neverSetAsRequired": false,
			"isReadOnly": false,
			"selectValues": null,
			"autoCompleteTags": null,
			"validationRegex": "",
			"x2_fields": "",
			"useAsKpi": false,
			"locked": false,
			"system": false,
			"content": false,
			"group": 0,
			"mergeStrategy": "",
			"hidden": false,
			"openEnded": false,
			"associatedTypes": null,
			"systemAssociatedTypes": null,
			"associatedToAll": true,
			"unmapped": false,
			"unsearchable": false,
			"caseInsensitive": true,
			"columns": null,
			"defaultRows": null,
			"sla": 0,
			"threshold": 72,
			"breachScript": "",
			"validatedError": "",
			"aliases": null,
			"aliasTo": "",
			"XDRBuiltInField": false,
			"selectValuesMap": null,
			"ipVersion": "",
			"pretty_name": "AIRS TSG ID",
			"XDRSpecialUpdateFlowField": false,
			"XsiamIncidentFieldExtraData": {
				"incidentsFilter": null,
				"slaGoals": null,
				"slaTimer": null,
				"timerConditions": null
			}
		},
		{
			"id": "incident_airsviolationbreakdown",
			"version": 0,
			"cacheVersn": 0,
			"modified": "2026-05-06T07:19:07.29685129Z",
			"sizeInBytes": 0,
			"packID": "",
			"packName": "",
			"itemVersion": "",
			"fromServerVersion": "",
			"toServerVersion": "",
			"definitionId": "",
			"isOverridable": false,
			"vcShouldIgnore": false,
			"vcShouldKeepItemLegacyProdMachine": false,
			"commitMessage": "",
			"shouldCommit": false,
			"name": "AIRS Violation Breakdown",
			"prevName": "",
			"ownerOnly": false,
			"placeholder": "",
			"template": "",
			"description": "",
			"cliName": "airsviolationbreakdown",
			"type": "shortText",
			"orgType": "shortText",
			"closeForm": false,
			"editForm": true,
			"required": false,
			"script": "",
			"runScriptAfterUpdate": false,
			"fieldCalcScript": "",
			"neverSetAsRequired": false,
			"isReadOnly": false,
			"selectValues": null,
			"autoCompleteTags": null,
			"validationRegex": "",
			"x2_fields": "",
			"useAsKpi": false,
			"locked": false,
			"system": false,
			"content": false,
			"group": 0,
			"mergeStrategy": "",
			"hidden": false,
			"openEnded": false,
			"associatedTypes": null,
			"systemAssociatedTypes": null,
			"associatedToAll": true,
			"unmapped": false,
			"unsearchable": false,
			"caseInsensitive": true,
			"columns": null,
			"defaultRows": null,
			"sla": 0,
			"threshold": 72,
			"breachScript": "",
			"validatedError": "",
			"aliases": null,
			"aliasTo": "",
			"XDRBuiltInField": false,
			"selectValuesMap": null,
			"ipVersion": "",
			"pretty_name": "AIRS Violation Breakdown",
			"XDRSpecialUpdateFlowField": false,
			"XsiamIncidentFieldExtraData": {
				"incidentsFilter": null,
				"slaGoals": null,
				"slaTimer": null,
				"timerConditions": null
			}
		},
		{
			"id": "incident_airsviolationstatus",
			"version": 0,
			"cacheVersn": 0,
			"modified": "2026-05-06T07:19:07.296852476Z",
			"sizeInBytes": 0,
			"packID": "",
			"packName": "",
			"itemVersion": "",
			"fromServerVersion": "",
			"toServerVersion": "",
			"definitionId": "",
			"isOverridable": false,
			"vcShouldIgnore": false,
			"vcShouldKeepItemLegacyProdMachine": false,
			"commitMessage": "",
			"shouldCommit": false,
			"name": "AIRS Violation Status",
			"prevName": "",
			"ownerOnly": false,
			"placeholder": "",
			"template": "",
			"description": "",
			"cliName": "airsviolationstatus",
			"type": "shortText",
			"orgType": "shortText",
			"closeForm": false,
			"editForm": true,
			"required": false,
			"script": "",
			"runScriptAfterUpdate": false,
			"fieldCalcScript": "",
			"neverSetAsRequired": false,
			"isReadOnly": false,
			"selectValues": null,
			"autoCompleteTags": null,
			"validationRegex": "",
			"x2_fields": "",
			"useAsKpi": false,
			"locked": false,
			"system": false,
			"content": false,
			"group": 0,
			"mergeStrategy": "",
			"hidden": false,
			"openEnded": false,
			"associatedTypes": [
				"Prisma AIRS Violation"
			],
			"systemAssociatedTypes": null,
			"associatedToAll": false,
			"unmapped": false,
			"unsearchable": true,
			"caseInsensitive": false,
			"columns": null,
			"defaultRows": null,
			"sla": 0,
			"threshold": 72,
			"breachScript": "",
			"validatedError": "",
			"aliases": null,
			"aliasTo": "",
			"XDRBuiltInField": false,
			"selectValuesMap": null,
			"ipVersion": "",
			"pretty_name": "AIRS Violation Status",
			"XDRSpecialUpdateFlowField": false,
			"XsiamIncidentFieldExtraData": null
		}
	]
}